{"card_name": "Guardian of the Cosmos", "color": "R", "rarity": "uncommon", "type": "Creature \u2013 Human Wizard", "number": 140, "color_identity": "R", "cost": "{3}{R}", "rules_text": "Whenever you cast an instant or sorcery spell, this creature deals 2 damage to each opponent.", "pt": "3/3", "special_text": "", "shape": "adventure", "set": "CNF", "loyalty": "", "card_name2": "Star's Potential", "color2": "R", "type2": "Instant \u2013 Adventure", "cost2": "{2}{R}", "rules_text2": "Copy target instant or sorcery spell you control. You may choose new targets for the copy. [i](Then exile this card. You may cast the creature later from exile.)[/i]", "pt2": "", "special_text2": "", "loyalty2": "", "notes": "!tag twink", "image_type": "png"}