{"card_name": "Bionic Rallier", "color": "W", "rarity": "uncommon", "type": "Creature \u2013 Human Wizard", "number": 4, "color_identity": "W", "cost": "{4}{W}", "rules_text": "[i]Landfall[/i] \u2013 Whenever a land you control enters, choose one\u2013\n\u2022 Create a 1/1 colorless Soldier artifact creature token.\n\u2022 Create a tapped Relic token. [i](It\u2019s an artifact with \u201c{T}: Add {C}. You can\u2019t spend this mana to cast your first spell each turn.\u201d)[/i]", "pt": "3/4", "special_text": "", "shape": "normal", "set": "CNF", "loyalty": "", "notes": "", "image_type": "png"}