{"card_name": "Magister of Control", "color": "U", "rarity": "uncommon", "type": "Creature \u2013 Human Wizard", "number": 67, "color_identity": "U", "cost": "{2}{U}", "rules_text": "Flying\nWhenever an opponent casts their first noncreature spell each turn, this creature connives. [i](Draw a card, then discard a card. If you discarded a nonland card, put a +1/+1 counter on this creature.)[/i]", "pt": "2/2", "special_text": "", "shape": "normal", "set": "CNF", "loyalty": "", "notes": "", "image_type": "png"}