{"card_name": "Runewarper", "color": "B", "rarity": "uncommon", "type": "Creature \u2013 Horror", "number": 114, "color_identity": "B", "cost": "{7}{B}{B}", "rules_text": "Pyre [i](Each creature you tap while casting this spell pays for {1}. Each other creature you sacrifice pays for {2} instead.)[/i]\nWhen Runewarper enters the battlefield, each opponent loses 1 life for each creature card in your graveyard.", "pt": "6/5", "special_text": "", "shape": "normal", "set": "KLA", "loyalty": "", "notes": ""}