{"card_name": "In Glory", "color": "G", "rarity": "common", "type": "Sorcery", "number": 186, "color_identity": "G", "cost": "{G}", "rules_text": "Choose one\u2013\n\u2022 Search your library for a basic land card, reveal it, put it into your hand, then shuffle.\n\u2022 Stargaze. [i](Reveal a Luminary you own from outside the game to put it into your hand and/or activate its cluster ability without paying its generic cost.)[/i]", "pt": "", "special_text": "", "shape": "normal", "set": "KLA", "loyalty": "", "notes": "", "image_type": "png"}