{"card_name": "Skodir, Reborn", "color": "WR", "rarity": "mythic", "type": "Legendary Creature \u2013 Human Warrior", "number": 244, "color_identity": "WRG", "cost": "{2}{R}{W}", "rules_text": "Haste\nWhenever Skodir, Reborn attacks, choose target creature you control. You may cast a copy of its Adventure. [i](You still pay its costs.)[/i]", "pt": "4/4", "special_text": "", "shape": "adventure", "set": "KLA", "loyalty": "", "card_name2": "Serpent's Bane", "color2": "WRG", "type2": "Instant \u2013 Adventure", "cost2": "{R}{W}", "rules_text2": "Serpent\u2019s Bane deals 2 damage to any target and you gain 2 life. [i](Then exile this card. You may cast the creature later from exile.)[/i]", "pt2": "", "special_text2": "", "loyalty2": "", "notes": ""}